Workbook

Sheet Read Me
A1: Illustrative Integrated Retail Financial Model
A3: Purpose | B3: Synthetic but internally linked model designed to stress-test the Financial Model Impact Analyzer.
A4: Company | B4: Illustrative RetailCo — not actual Reliance Retail financial data.
A5: Period | B5: Quarterly model covering Q1 FY25A through Q4 FY28E.
A6: Model depth | B6: Operating drivers → segment revenue → P&L → balance sheet → cash flow → valuation.
A7: Key test | B7: Management guidance should map to assumptions and then trace through formulas to downstream outputs.
A8: Important | B8: All figures are illustrative. Do not use this workbook for investment decisions.
A11: Suggested demo flow
A12: 1. Upload this model.
A13: 2. Upload the companion sample earnings-call transcript.
A14: 3. Upload the companion analyst notes.
A15: 4. Ask the agent to identify forecast/assumption cells affected by management guidance.
A16: 5. Validate that it distinguishes direct assumption changes from derived formula impacts.

Sheet Assumptions
A1: Core Forecast Assumptions
A2: Assumption | B2: Unit | C2: FY26E | D2: FY27E | E2: FY28E | F2: Source / Logic
A3: Retail Revenue Growth | B3: % | C3: 0.095 | D3: 0.105 | E3: 0.115 | F3: Management / analyst scenario
A4: Fashion Growth | B4: % | C4: 0.07 | D4: 0.085 | E4: 0.095 | F4: Category outlook
A5: Grocery Growth | B5: % | C5: 0.12 | D5: 0.125 | E5: 0.13 | F5: Store expansion + same-store growth
A6: Consumer Electronics Growth | B6: % | C6: 0.085 | D6: 0.095 | E6: 0.1 | F6: Demand + digital mix
A7: Digital Commerce Growth | B7: % | C7: 0.18 | D7: 0.17 | E7: 0.16 | F7: Management commentary
A8: EBITDA Margin | B8: % | C8: 0.108 | D8: 0.112 | E8: 0.117 | F8: Operating leverage assumption
A9: Gross Margin | B9: % | C9: 0.28 | D9: 0.285 | E9: 0.29 | F9: Mix / scale assumption
A10: Store Additions | B10: stores | C10: 720 | D10: 780 | E10: 850 | F10: Expansion plan
A11: Store Closure Rate | B11: % | C11: 0.01 | D11: 0.01 | E11: 0.01 | F11: Normal churn
A12: Same Store Sales Growth | B12: % | C12: 0.06 | D12: 0.065 | E12: 0.07 | F12: Base case
A13: Capex | B13: ₹ bn | C13: 32 | D13: 36 | E13: 41 | F13: Store + digital investment
A14: D&A / Capex | B14: % | C14: 0.46 | D14: 0.465 | E14: 0.47 | F14: Asset mix
... A20: Terminal Growth | B20: % | C20: 0.04 | D20: 0.04 | E20: 0.04 | F20: DCF assumption

Sheet Operating Metrics
A1: Quarterly Operating Drivers
A2: Metric | B2: Q1 FY25A | C2: Q2 FY25A | D2: Q3 FY25A | E2: Q4 FY25A | F2: Q1 FY26A | G2: Q2 FY26A | H2: Q3 FY26A | I2: Q4 FY26E | J2: Q1 FY27E | K2: Q2 FY27E | L2: Q3 FY27E | M2: Q4 FY27E | N2: Q1 FY28E | O2: Q2 FY28E | P2: Q3 FY28E | Q2: Q4 FY28E
A3: Store Count | B3: 1500 | C3: 1540 | D3: 1585 | E3: 1630 | F3: 1680 | G3: 1735 | H3: 1790 | I3: 1850 | J3: 1920 | K3: 1990 | L3: 2060 | M3: 2130 | N3: 2210 | O3: 2290 | P3: 2370 | Q3: 2450
A4: New Stores | B4: 35 | C4: 40 | D4: 45 | E4: 45 | F4: 50 | G4: 55 | H4: 55 | I4: 60 | J4: 70 | K4: 70 | L4: 70 | M4: 70 | N4: 80 | O4: 80 | P4: 80 | Q4: 80
A5: Store Closures | B5: 5 | C5: 5 | D5: 0 | E5: 0 | F5: 0 | G5: 0 | H5: 0 | I5: 0 | J5: 0 | K5: 0 | L5: 0 | M5: 0 | N5: 0 | O5: 0 | P5: 0 | Q5: 0
A6: Same Store Sales Growth | B6: 0.04 | C6: 0.045 | D6: 0.05 | E6: 0.055 | F6: 0.055 | G6: 0.06 | H6: 0.06 | I6: 0.06 | J6: 0.06 | K6: 0.065 | L6: 0.065 | M6: 0.065 | N6: 0.07 | O6: 0.07 | P6: 0.07 | Q6: 0.07
A7: Digital Mix | B7: 0.12 | C7: 0.125 | D7: 0.13 | E7: 0.135 | F7: 0.14 | G7: 0.145 | H7: 0.15 | I7: 0.155 | J7: 0.16 | K7: 0.165 | L7: 0.17 | M7: 0.175 | N7: 0.18 | O7: 0.185 | P7: 0.19 | Q7: 0.195
A8: Employees (000s) | B8: 95 | C8: 98 | D8: 101 | E8: 104 | F8: 108 | G8: 112 | H8: 116 | I8: 120 | J8: 126 | K8: 132 | L8: 138 | M8: 144 | N8: 151 | O8: 158 | P8: 165 | Q8: 172
A9: Store Productivity Index | B9: 1 | C9: 1.01 | D9: 1.02 | E9: 1.03 | F9: 1.04 | G9: 1.05 | H9: 1.06 | I9: 1.07 | J9: 1.08 | K9: 1.09 | L9: 1.1 | M9: 1.11 | N9: 1.12 | O9: 1.13 | P9: 1.14 | Q9: 1.15

Sheet Segment Revenue
A1: Segment Revenue Build
A2: ₹ bn | B2: Q1 FY25A | C2: Q2 FY25A | D2: Q3 FY25A | E2: Q4 FY25A | F2: Q1 FY26A | G2: Q2 FY26A | H2: Q3 FY26A | I2: Q4 FY26E | J2: Q1 FY27E | K2: Q2 FY27E | L2: Q3 FY27E | M2: Q4 FY27E | N2: Q1 FY28E | O2: Q2 FY28E | P2: Q3 FY28E | Q2: Q4 FY28E
A3: Grocery | B3: 24 | C3: 25 | D3: 26 | E3: 28 | F3: 29 | G3: 31 | H3: 33 | I3: 35 | J3: 37 | K3: 39 | L3: 41 | M3: 43 | N3: 46 | O3: 49 | P3: 52 | Q3: 55
A4: Fashion | B4: 12 | C4: 13 | D4: 14 | E4: 15 | F4: 14 | G4: 15 | H4: 16 | I4: 17 | J4: 16 | K4: 17 | L4: 18 | M4: 19 | N4: 18 | O4: 19 | P4: 20 | Q4: 21
A5: Consumer Electronics | B5: 18 | C5: 19 | D5: 20 | E5: 22 | F5: 21 | G5: 22 | H5: 23 | I5: 24 | J5: 23 | K5: 24 | L5: 25 | M5: 26 | N5: 25 | O5: 26 | P5: 27 | Q5: 28
A6: Digital Commerce | B6: 8 | C6: 9 | D6: 10 | E6: 11 | F6: 11 | G6: 12 | H6: 13 | I6: 14 | J6: 14 | K6: 15 | L6: 16 | M6: 17 | N6: 17 | O6: 18 | P6: 19 | Q6: 20
A7: Other Retail | B7: 6 | C7: 6.5 | D7: 7 | E7: 7.5 | F7: 7 | G7: 7.5 | H7: 8 | I7: 8.5 | J7: 8 | K7: 8.5 | L7: 9 | M7: 9.5 | N7: 9 | O7: 9.5 | P7: 10 | Q7: 10.5
A8: Total Revenue | B8: =SUM(B3:B7) | C8: =SUM(C3:C7) | D8: =SUM(D3:D7) | E8: =SUM(E3:E7) | F8: =SUM(F3:F7) | G8: =SUM(G3:G7) | H8: =SUM(H3:H7) | I8: =SUM(I3:I7) | ... Q8: =SUM(Q3:Q7)
A9: YoY Growth | F9: =F8/B8-1 | G9: =G8/C8-1 | H9: =H8/D8-1 | I9: =I8/E8-1 | J9: =J8/F8-1 | K9: =K8/G8-1 | L9: =L8/H8-1 | M9: =M8/I8-1 | ... Q9: =Q8/M8-1
A10: Digital % of Revenue | B10: =B6/B8 | C10: =C6/C8 | D10: =D6/D8 | E10: =E6/E8 | F10: =F6/F8 | G10: =G6/G8 | H10: =H6/H8 | I10: =I6/I8 | ... Q10: =Q6/Q8

Sheet P&L
A1: Quarterly Profit & Loss
A2: ₹ bn | B2: Q1 FY25A | C2: Q2 FY25A | D2: Q3 FY25A | E2: Q4 FY25A | F2: Q1 FY26A | G2: Q2 FY26A | H2: Q3 FY26A | I2: Q4 FY26E | J2: Q1 FY27E | K2: Q2 FY27E | L2: Q3 FY27E | M2: Q4 FY27E | N2: Q1 FY28E | O2: Q2 FY28E | P2: Q3 FY28E | Q2: Q4 FY28E
A3: Revenue | B3: ='Segment Revenue'!B8 | C3: ='Segment Revenue'!C8 | D3: ='Segment Revenue'!D8 | E3: ='Segment Revenue'!E8 | F3: ='Segment Revenue'!F8 | G3: ='Segment Revenue'!G8 | H3: ='Segment Revenue'!H8 | I3: ='Segment Revenue'!I8 | ... Q3: ='Segment Revenue'!Q8
A4: COGS | B4: =B3*(1-IF(B$2="Q4 FY26E",Assumptions!$D$9,IF(B$2="Q4 FY27E",Assumptions!$E$9,IF(B$2="Q4 FY28E",Assumptions!$F$9,0.72)))) | C4: =C3*(1-IF(C$2="Q4 FY26E",Assumptions!$D$9,IF(C$2="Q4 FY27E",Assumptions!$E$9,IF(C$2="Q4 FY28E",Assumptions!$F$9,0.72)))) | D4: =D3*(1-IF(D$2="Q4 FY26E",Assumptions!$D$9,IF(D$2="Q4 FY27E",Assumptions!$E$9,IF(D$2="Q4 FY28E",Assumptions!$F$9,0.72)))) | E4: =E3*(1-IF(E$2="Q4 FY26E",Assumptions!$D$9,IF(E$2="Q4 FY27E",Assumptions!$E$9,IF(E$2="Q4 FY28E",Assumptions!$F$9,0.72)))) | F4: =F3*(1-IF(F$2="Q4 FY26E",Assumptions!$D$9,IF(F$2="Q4 FY27E",Assumptions!$E$9,IF(F$2="Q4 FY28E",Assumptions!$F$9,0.72)))) | G4: =G3*(1-IF(G$2="Q4 FY26E",Assumptions!$D$9,IF(G$2="Q4 FY27E",Assumptions!$E$9,IF(G$2="Q4 FY28E",Assumptions!$F$9,0.72)))) | H4: =H3*(1-IF(H$2="Q4 FY26E",Assumptions!$D$9,IF(H$2="Q4 FY27E",Assumptions!$E$9,IF(H$2="Q4 FY28E",Assumptions!$F$9,0.72)))) | I4: =I3*(1-IF(I$2="Q4 FY26E",Assumptions!$D$9,IF(I$2="Q4 FY27E",Assumptions!$E$9,IF(I$2="Q4 FY28E",Assumptions!$F$9,0.72)))) | ... Q4: =Q3*(1-IF(Q$2="Q4 FY26E",Assumptions!$D$9,IF(Q$2="Q4 FY27E",Assumptions!$E$9,IF(Q$2="Q4 FY28E",Assumptions!$F$9,0.72))))
A5: Gross Profit | B5: =B3-B4 | C5: =C3-C4 | D5: =D3-D4 | E5: =E3-E4 | F5: =F3-F4 | G5: =G3-G4 | H5: =H3-H4 | I5: =I3-I4 | ... Q5: =Q3-Q4
A6: Gross Margin | B6: =B5/B3 | C6: =C5/C3 | D6: =D5/D3 | E6: =E5/E3 | F6: =F5/F3 | G6: =G5/G3 | H6: =H5/H3 | I6: =I5/I3 | ... Q6: =Q5/Q3
A7: Operating Expenses | B7: =B3*0.172 | C7: =C3*0.172 | D7: =D3*0.172 | E7: =E3*0.172 | F7: =F3*0.172 | G7: =G3*0.172 | H7: =H3*0.172 | I7: =I3*0.172 | J7: =J3*(1-IF(J$2="Q4 FY26E",Assumptions!$D$8,IF(J$2="Q4 FY27E",Assumptions!$E$8,Assumptions!$F$8))-0.72) | K7: =K3*(1-IF(K$2="Q4 FY26E",Assumptions!$D$8,IF(K$2="Q4 FY27E",Assumptions!$E$8,Assumptions!$F$8))-0.72) | L7: =L3*(1-IF(L$2="Q4 FY26E",Assumptions!$D$8,IF(L$2="Q4 FY27E",Assumptions!$E$8,Assumptions!$F$8))-0.72) | M7: =M3*(1-IF(M$2="Q4 FY26E",Assumptions!$D$8,IF(M$2="Q4 FY27E",Assumptions!$E$8,Assumptions!$F$8))-0.72) | N7: =N3*(1-IF(N$2="Q4 FY26E",Assumptions!$D$8,IF(N$2="Q4 FY27E",Assumptions!$E$8,Assumptions!$F$8))-0.72) | O7: =O3*(1-IF(O$2="Q4 FY26E",Assumptions!$D$8,IF(O$2="Q4 FY27E",Assumptions!$E$8,Assumptions!$F$8))-0.72) | P7: =P3*(1-IF(P$2="Q4 FY26E",Assumptions!$D$8,IF(P$2="Q4 FY27E",Assumptions!$E$8,Assumptions!$F$8))-0.72) | Q7: =Q3*(1-IF(Q$2="Q4 FY26E",Assumptions!$D$8,IF(Q$2="Q4 FY27E",Assumptions!$E$8,Assumptions!$F$8))-0.72)
A8: EBITDA | B8: =B5-B7 | C8: =C5-C7 | D8: =D5-D7 | E8: =E5-E7 | F8: =F5-F7 | G8: =G5-G7 | H8: =H5-H7 | I8: =I5-I7 | ... Q8: =Q5-Q7
A9: EBITDA Margin | B9: =B8/B3 | C9: =C8/C3 | D9: =D8/D3 | E9: =E8/E3 | F9: =F8/F3 | G9: =G8/G3 | H9: =H8/H3 | I9: =I8/I3 | ... Q9: =Q8/Q3
A10: D&A | B10: =B8*0.20 | C10: =C8*0.20 | D10: =D8*0.20 | E10: =E8*0.20 | F10: =F8*0.20 | G10: =G8*0.20 | H10: =H8*0.20 | I10: =I8*0.20 | J10: ='Cash Flow'!J15 | K10: ='Cash Flow'!K15 | L10: ='Cash Flow'!L15 | M10: ='Cash Flow'!M15 | N10: ='Cash Flow'!N15 | O10: ='Cash Flow'!O15 | P10: ='Cash Flow'!P15 | Q10: ='Cash Flow'!Q15
A11: EBIT | B11: =B8-B10 | C11: =C8-C10 | D11: =D8-D10 | E11: =E8-E10 | F11: =F8-F10 | G11: =G8-G10 | H11: =H8-H10 | I11: =I8-I10 | ... Q11: =Q8-Q10
A12: Interest Expense | B12: =B3*0.012 | C12: =C3*0.012 | D12: =D3*0.012 | E12: =E3*0.012 | F12: =F3*0.012 | G12: =G3*0.012 | H12: =H3*0.012 | I12: ='Balance Sheet'!I19*IF(I$2="Q4 FY26E",Assumptions!$D$19,IF(I$2="Q4 FY27E",Assumptions!$E$19,Assumptions!$F$19))/4 | J12: ='Balance Sheet'!J19*IF(J$2="Q4 FY26E",Assumptions!$D$19,IF(J$2="Q4 FY27E",Assumptions!$E$19,Assumptions!$F$19))/4 | K12: ='Balance Sheet'!K19*IF(K$2="Q4 FY26E",Assumptions!$D$19,IF(K$2="Q4 FY27E",Assumptions!$E$19,Assumptions!$F$19))/4 | L12: ='Balance Sheet'!L19*IF(L$2="Q4 FY26E",Assumptions!$D$19,IF(L$2="Q4 FY27E",Assumptions!$E$19,Assumptions!$F$19))/4 | M12: ='Balance Sheet'!M19*IF(M$2="Q4 FY26E",Assumptions!$D$19,IF(M$2="Q4 FY27E",Assumptions!$E$19,Assumptions!$F$19))/4 | N12: ='Balance Sheet'!N19*IF(N$2="Q4 FY26E",Assumptions!$D$19,IF(N$2="Q4 FY27E",Assumptions!$E$19,Assumptions!$F$19))/4 | O12: ='Balance Sheet'!O19*IF(O$2="Q4 FY26E",Assumptions!$D$19,IF(O$2="Q4 FY27E",Assumptions!$E$19,Assumptions!$F$19))/4 | P12: ='Balance Sheet'!P19*IF(P$2="Q4 FY26E",Assumptions!$D$19,IF(P$2="Q4 FY27E",Assumptions!$E$19,Assumptions!$F$19))/4 | Q12: ='Balance Sheet'!Q19*IF(Q$2="Q4 FY26E",Assumptions!$D$19,IF(Q$2="Q4 FY27E",Assumptions!$E$19,Assumptions!$F$19))/4
A13: EBT | B13: =B11-B12 | C13: =C11-C12 | D13: =D11-D12 | E13: =E11-E12 | F13: =F11-F12 | G13: =G11-G12 | H13: =H11-H12 | I13: =I11-I12 | ... Q13: =Q11-Q12
A14: Tax | B14: =MAX(0,B13*0.25) | C14: =MAX(0,C13*0.25) | D14: =MAX(0,D13*0.25) | E14: =MAX(0,E13*0.25) | F14: =MAX(0,F13*0.25) | G14: =MAX(0,G13*0.25) | H14: =MAX(0,H13*0.25) | I14: =MAX(0,I13*0.25) | ... Q14: =MAX(0,Q13*0.25)
A15: Net Income | B15: =B13-B14 | C15: =C13-C14 | D15: =D13-D14 | E15: =E13-E14 | F15: =F13-F14 | G15: =G13-G14 | H15: =H13-H14 | I15: =I13-I14 | ... Q15: =Q13-Q14
A16: EPS | B16: =B15/25 | C16: =C15/25 | D16: =D15/25 | E16: =E15/25 | F16: =F15/25 | G16: =G15/25 | H16: =H15/25 | I16: =I15/25 | ... Q16: =Q15/25

Sheet Balance Sheet
A1: Quarterly Balance Sheet
A2: ₹ bn | B2: Q1 FY25A | C2: Q2 FY25A | D2: Q3 FY25A | E2: Q4 FY25A | F2: Q1 FY26A | G2: Q2 FY26A | H2: Q3 FY26A | I2: Q4 FY26E | J2: Q1 FY27E | K2: Q2 FY27E | L2: Q3 FY27E | M2: Q4 FY27E | N2: Q1 FY28E | O2: Q2 FY28E | P2: Q3 FY28E | Q2: Q4 FY28E
A3: Cash & Equivalents | B3: 18 | C3: 19 | D3: 21 | E3: 23 | F3: 24 | G3: 25 | H3: 26 | I3: 27 | J3: 28 | K3: 30 | L3: 31 | M3: 33 | N3: 35 | O3: 37 | P3: 39 | Q3: 42
A4: Accounts Receivable | B4: 5 | C4: 5.2 | D4: 5.4 | E4: 5.6 | F4: 5.8 | G4: 6 | H4: 6.2 | I4: 6.5 | J4: 6.8 | K4: 7 | L4: 7.2 | M4: 7.5 | N4: 7.8 | O4: 8 | P4: 8.2 | Q4: 8.5
A5: Inventory | B5: 30 | C5: 31 | D5: 32 | E5: 34 | F5: 35 | G5: 36 | H5: 37 | I5: 38 | J5: 39 | K5: 40 | L5: 41 | M5: 42 | N5: 43 | O5: 44 | P5: 45 | Q5: 46
A6: PP&E | B6: 90 | C6: 92 | D6: 95 | E6: 98 | F6: 101 | G6: 104 | H6: 107 | I6: 110 | J6: 114 | K6: 118 | L6: 122 | M6: 126 | N6: 131 | O6: 136 | P6: 141 | Q6: 146
A7: Other Assets | B7: 12 | C7: 12.5 | D7: 13 | E7: 13.5 | F7: 14 | G7: 14.5 | H7: 15 | I7: 15.5 | J7: 16 | K7: 16.5 | L7: 17 | M7: 17.5 | N7: 18 | O7: 18.5 | P7: 19 | Q7: 19.5
A8: Total Assets | B8: =SUM(B3:B7) | C8: =SUM(C3:C7) | D8: =SUM(D3:D7) | E8: =SUM(E3:E7) | F8: =SUM(F3:F7) | G8: =SUM(G3:G7) | H8: =SUM(H3:H7) | I8: =SUM(I3:I7) | ... Q8: =SUM(Q3:Q7)
A9: Accounts Payable | B9: 20 | C9: 21 | D9: 22 | E9: 23 | F9: 24 | G9: 25 | H9: 26 | I9: 27 | J9: 28 | K9: 29 | L9: 30 | M9: 31 | N9: 32 | O9: 33 | P9: 34 | Q9: 35
A10: Other Current Liabilities | B10: 12 | C10: 12.5 | D10: 13 | E10: 13.5 | F10: 14 | G10: 14.5 | H10: 15 | I10: 15.5 | J10: 16 | K10: 16.5 | L10: 17 | M10: 17.5 | N10: 18 | O10: 18.5 | P10: 19 | Q10: 19.5
A11: Debt | B11: 35 | C11: 36 | D11: 37 | E11: 38 | F11: 39 | G11: 40 | H11: 41 | I11: 42 | J11: 43 | K11: 44 | L11: 45 | M11: 46 | N11: 47 | O11: 48 | P11: 49 | Q11: 50
A12: Equity | B12: 88 | C12: 90.2 | D12: 91.4 | E12: 94.6 | F12: 95.8 | G12: 97 | H12: 98.2 | I12: 99.5 | J12: 101 | K12: 103 | L12: 105 | M12: 107 | N12: 110 | O12: 113 | P12: 116 | Q12: 119
A13: Other Liabilities | B13: 0 | C13: 0 | D13: 0 | E13: 0 | F13: 0 | G13: 0 | H13: 0 | I13: 0 | J13: 0 | K13: 0 | L13: 0 | M13: 0 | N13: 0 | O13: 0 | P13: 0 | Q13: 0
A14: Total Liabilities & Equity | B14: =SUM(B9:B13) | C14: =SUM(C9:C13) | D14: =SUM(D9:D13) | E14: =SUM(E9:E13) | F14: =SUM(F9:F13) | G14: =SUM(G9:G13) | H14: =SUM(H9:H13) | I14: =SUM(I9:I13) | ... Q14: =SUM(Q9:Q13)
A15: Balance Check | B15: =B8-B14 | C15: =C8-C14 | D15: =D8-D14 | E15: =E8-E14 | F15: =F8-F14 | G15: =G8-G14 | H15: =H8-H14 | I15: =I8-I14 | ... Q15: =Q8-Q14

Sheet Cash Flow
A1: Quarterly Cash Flow
A2: ₹ bn | B2: Q1 FY25A | C2: Q2 FY25A | D2: Q3 FY25A | E2: Q4 FY25A | F2: Q1 FY26A | G2: Q2 FY26A | H2: Q3 FY26A | I2: Q4 FY26E | J2: Q1 FY27E | K2: Q2 FY27E | L2: Q3 FY27E | M2: Q4 FY27E | N2: Q1 FY28E | O2: Q2 FY28E | P2: Q3 FY28E | Q2: Q4 FY28E
A3: Net Income | B3: ='P&L'!B15 | C3: ='P&L'!C15 | D3: ='P&L'!D15 | E3: ='P&L'!E15 | F3: ='P&L'!F15 | G3: ='P&L'!G15 | H3: ='P&L'!H15 | I3: ='P&L'!I15 | ... Q3: ='P&L'!Q15
A4: D&A | B4: ='P&L'!B10 | C4: ='P&L'!C10 | D4: ='P&L'!D10 | E4: ='P&L'!E10 | F4: ='P&L'!F10 | G4: ='P&L'!G10 | H4: ='P&L'!H10 | I4: ='P&L'!I10 | ... Q4: ='P&L'!Q10
A5: Change in Working Capital | B5: -1 | C5: -1.2 | D5: -1.4 | E5: -1.5 | F5: -1.4 | G5: -1.5 | H5: -1.6 | I5: -1.8 | J5: -1.9 | K5: -2 | L5: -2.1 | M5: -2.2 | N5: -2.3 | O5: -2.4 | P5: -2.5 | Q5: -2.6
A6: Other Non-Cash Items | B6: =SUM(B3:B6) | C6: =SUM(C3:C6) | D6: =SUM(D3:D6) | E6: =SUM(E3:E6) | F6: =SUM(F3:F6) | G6: =SUM(G3:G6) | H6: =SUM(H3:H6) | I6: =SUM(I3:I6) | ... Q6: =SUM(Q3:Q6)
A7: Cash Flow from Operations
A8: Capex | B8: 4.5 | C8: 4.8 | D8: 5 | E8: 5.2 | F8: 6 | G8: 6.5 | H8: 7 | I8: 8 | J8: 8.5 | K8: 9 | L8: 9.5 | M8: 10 | N8: 10.5 | O8: 11 | P8: 11.5 | Q8: 12
A9: Acquisitions / Investments | B9: =-SUM(B7:B8) | C9: =-SUM(C7:C8) | D9: =-SUM(D7:D8) | E9: =-SUM(E7:E8) | F9: =-SUM(F7:F8) | G9: =-SUM(G7:G8) | H9: =-SUM(H7:H8) | I9: =-SUM(I7:I8) | ... Q9: =-SUM(Q7:Q8)
A10: Cash Flow from Investing
A11: Debt Issuance / (Repayment) | B11: 1 | C11: 1 | D11: 1 | E11: 1 | F11: 1 | G11: 1 | H11: 1 | I11: 1 | J11: 1 | K11: 1 | L11: 1 | M11: 1 | N11: 1 | O11: 1 | P11: 1 | Q11: 1
A12: Dividends | B12: =SUM(B10:B11) | C12: =SUM(C10:C11) | D12: =SUM(D10:D11) | E12: =SUM(E10:E11) | F12: =SUM(F10:F11) | G12: =SUM(G10:G11) | H12: =SUM(H10:H11) | I12: =SUM(I10:I11) | ... Q12: =SUM(Q10:Q11)
A13: Cash Flow from Financing | B13: =B6+B9+B12 | C13: =C6+C9+C12 | D13: =D6+D9+D12 | E13: =E6+E9+E12 | F13: =F6+F9+F12 | G13: =G6+G9+G12 | H13: =H6+H9+H12 | I13: =I6+I9+I12 | ... Q13: =Q6+Q9+Q12
A14: Net Change in Cash
A15: Beginning Cash | B15: =B13+B14 | C15: =C13+C14 | D15: =D13+D14 | E15: =E13+E14 | F15: =F13+F14 | G15: =G13+G14 | H15: =H13+H14 | I15: =I13+I14 | ... Q15: =Q13+Q14
A16: Ending Cash | B16: =B4/B7 | C16: =C4/C7 | D16: =D4/D7 | E16: =E4/E7 | F16: =F4/F7 | G16: =G4/G7 | H16: =H4/H7 | I16: =I4/I7 | ... Q16: =Q4/Q7
A17: D&A / Capex

Sheet Working Capital
A1: Working Capital Drivers
A2: Metric | B2: Q1 FY25A | C2: Q2 FY25A | D2: Q3 FY25A | E2: Q4 FY25A | F2: Q1 FY26A | G2: Q2 FY26A | H2: Q3 FY26A | I2: Q4 FY26E | J2: Q1 FY27E | K2: Q2 FY27E | L2: Q3 FY27E | M2: Q4 FY27E | N2: Q1 FY28E | O2: Q2 FY28E | P2: Q3 FY28E | Q2: Q4 FY28E
A3: DSO | B3: 12 | C3: 12 | D3: 12 | E3: 12 | F3: 12 | G3: 12 | H3: 12 | I3: 12 | J3: 12 | K3: 12 | L3: 12 | M3: 12 | N3: 12 | O3: 12 | P3: 12 | Q3: 12
A4: Inventory Days | B4: 45 | C4: 45 | D4: 44 | E4: 44 | F4: 43 | G4: 43 | H4: 42 | I4: 42 | J4: 41 | K4: 41 | L4: 41 | M4: 40 | N4: 40 | O4: 40 | P4: 40 | Q4: 40
A5: DPO | B5: 34 | C5: 34 | D5: 34 | E5: 35 | F5: 35 | G5: 35 | H5: 36 | I5: 36 | J5: 36 | K5: 36 | L5: 37 | M5: 37 | N5: 37 | O5: 37 | P5: 37 | Q5: 37
A6: AR | B6: 5 | C6: 5.2 | D6: 5.4 | E6: 5.6 | F6: 5.8 | G6: 6 | H6: 6.2 | I6: 6.5 | J6: 6.8 | K6: 7 | L6: 7.2 | M6: 7.5 | N6: 7.8 | O6: 8 | P6: 8.2 | Q6: 8.5
A7: Inventory | B7: 30 | C7: 31 | D7: 32 | E7: 34 | F7: 35 | G7: 36 | H7: 37 | I7: 38 | J7: 39 | K7: 40 | L7: 41 | M7: 42 | N7: 43 | O7: 44 | P7: 45 | Q7: 46
A8: AP | B8: 20 | C8: 21 | D8: 22 | E8: 23 | F8: 24 | G8: 25 | H8: 26 | I8: 27 | J8: 28 | K8: 29 | L8: 30 | M8: 31 | N8: 32 | O8: 33 | P8: 34 | Q8: 35

Sheet DCF Valuation
A1: Illustrative DCF Valuation
A2: Metric | B2: FY27E | C2: FY28E | D2: FY29E | E2: FY30E | F2: FY31E
A3: Revenue | B3: ='P&L'!J3 | C3: ='P&L'!N3 | D3: =C3*1.09 | E3: =D3*1.08 | F3: =E3*1.07
A4: EBITDA Margin | B4: 0.112 | C4: 0.117 | D4: 0.119 | E4: 0.12 | F4: 0.12
A5: EBITDA | B5: =B3*B4 | C5: =C3*C4 | D5: =D3*D4 | E5: =E3*E4 | F5: =F3*F4
A6: D&A | B6: ='P&L'!J10 | C6: ='P&L'!N10 | D6: =D5*0.20 | E6: =E5*0.20 | F6: =F5*0.20
A7: EBIT | B7: =B5-B6 | C7: =C5-C6 | D7: =D5-D6 | E7: =E5-E6 | F7: =F5-F6
A8: Tax Rate | B8: 0.25 | C8: 0.25 | D8: 0.25 | E8: 0.25 | F8: 0.25
A9: NOPAT | B9: =B7*(1-B8) | C9: =C7*(1-C8) | D9: =D7*(1-D8) | E9: =E7*(1-E8) | F9: =F7*(1-F8)
A10: D&A Add-back | B10: =B6 | C10: =C6 | D10: =D6 | E10: =E6 | F10: =F6
A11: Capex | B11: -36 | C11: -41 | D11: -43 | E11: -45 | F11: -47
A12: Change in NWC | B12: -5 | C12: -5.5 | D12: -5.8 | E12: -6 | F12: -6.2
A13: FCFF | B13: =SUM(B9:B12) | C13: =SUM(C9:C12) | D13: =SUM(D9:D12) | E13: =SUM(E9:E12) | F13: =SUM(F9:F12)
A14: WACC | B14: 0.095 | C14: 0.095 | D14: 0.095 | E14: 0.095 | F14: 0.095
A15: Discount Factor | B15: =1/(1+B14)^1 | C15: =1/(1+C14)^2 | D15: =1/(1+D14)^3 | E15: =1/(1+E14)^4 | F15: =1/(1+F14)^5
A16: PV of FCFF | B16: =B13*B15 | C16: =C13*C15 | D16: =D13*D15 | E16: =E13*E15 | F16: =F13*F15
A17: Terminal Growth | B17: 0.04
A18: Terminal Value | B18: =F13*(1+B17)/(B14-B17)
A19: PV of Terminal Value | B19: =B18*F15
A20: Enterprise Value | B20: =SUM(B16:F16)+B19
A21: Net Debt | B21: 20
A22: Illustrative Equity Value | B22: =B20-B21

Sheet Ratios
A1: Key Financial Ratios
A2: Ratio | B2: Q1 FY25A | C2: Q2 FY25A | D2: Q3 FY25A | E2: Q4 FY25A | F2: Q1 FY26A | G2: Q2 FY26A | H2: Q3 FY26A | I2: Q4 FY26E | J2: Q1 FY27E | K2: Q2 FY27E | L2: Q3 FY27E | M2: Q4 FY27E | N2: Q1 FY28E | O2: Q2 FY28E | P2: Q3 FY28E | Q2: Q4 FY28E
A3: Revenue Growth | F3: ='P&L'!F3/'P&L'!B3-1 | G3: ='P&L'!G3/'P&L'!C3-1 | H3: ='P&L'!H3/'P&L'!D3-1 | I3: ='P&L'!I3/'P&L'!E3-1 | J3: ='P&L'!J3/'P&L'!F3-1 | K3: ='P&L'!K3/'P&L'!G3-1 | L3: ='P&L'!L3/'P&L'!H3-1 | M3: ='P&L'!M3/'P&L'!I3-1 | ... Q3: ='P&L'!Q3/'P&L'!M3-1
A4: EBITDA Margin | B4: ='P&L'!B9 | C4: ='P&L'!C9 | D4: ='P&L'!D9 | E4: ='P&L'!E9 | F4: ='P&L'!F9 | G4: ='P&L'!G9 | H4: ='P&L'!H9 | I4: ='P&L'!I9 | ... Q4: ='P&L'!Q9
A5: Net Margin | B5: ='P&L'!B15/'P&L'!B3 | C5: ='P&L'!C15/'P&L'!C3 | D5: ='P&L'!D15/'P&L'!D3 | E5: ='P&L'!E15/'P&L'!E3 | F5: ='P&L'!F15/'P&L'!F3 | G5: ='P&L'!G15/'P&L'!G3 | H5: ='P&L'!H15/'P&L'!H3 | I5: ='P&L'!I15/'P&L'!I3 | ... Q5: ='P&L'!Q15/'P&L'!Q3
A6: Debt / EBITDA | B6: ='Balance Sheet'!B11/'P&L'!B8 | C6: ='Balance Sheet'!C11/'P&L'!C8 | D6: ='Balance Sheet'!D11/'P&L'!D8 | E6: ='Balance Sheet'!E11/'P&L'!E8 | F6: ='Balance Sheet'!F11/'P&L'!F8 | G6: ='Balance Sheet'!G11/'P&L'!G8 | H6: ='Balance Sheet'!H11/'P&L'!H8 | I6: ='Balance Sheet'!I11/'P&L'!I8 | ... Q6: ='Balance Sheet'!Q11/'P&L'!Q8
A7: ROIC | B7: ='P&L'!B11/('Balance Sheet'!B11+'Balance Sheet'!B12) | C7: ='P&L'!C11/('Balance Sheet'!C11+'Balance Sheet'!C12) | D7: ='P&L'!D11/('Balance Sheet'!D11+'Balance Sheet'!D12) | E7: ='P&L'!E11/('Balance Sheet'!E11+'Balance Sheet'!E12) | F7: ='P&L'!F11/('Balance Sheet'!F11+'Balance Sheet'!F12) | G7: ='P&L'!G11/('Balance Sheet'!G11+'Balance Sheet'!G12) | H7: ='P&L'!H11/('Balance Sheet'!H11+'Balance Sheet'!H12) | I7: ='P&L'!I11/('Balance Sheet'!I11+'Balance Sheet'!I12) | ... Q7: ='P&L'!Q11/('Balance Sheet'!Q11+'Balance Sheet'!Q12)

Sheet Sensitivity
A1: DCF Sensitivity — Illustrative
A3: Equity Value Sensitivity to WACC / Terminal Growth
A5: WACC \ g | B5: 0.03 | C5: 0.035 | D5: 0.04 | E5: 0.045 | F5: 0.05
A6: 0.085 | B6: =('DCF Valuation'!F13*(1+B$5)/($A6-B$5))*'DCF Valuation'!F15+'DCF Valuation'!B16+'DCF Valuation'!C16+'DCF Valuation'!D16+'DCF Valuation'!E16+'DCF Valuation'!F16-'DCF Valuation'!B21 | C6: =('DCF Valuation'!F13*(1+C$5)/($A6-C$5))*'DCF Valuation'!F15+'DCF Valuation'!B16+'DCF Valuation'!C16+'DCF Valuation'!D16+'DCF Valuation'!E16+'DCF Valuation'!F16-'DCF Valuation'!B21 | D6: =('DCF Valuation'!F13*(1+D$5)/($A6-D$5))*'DCF Valuation'!F15+'DCF Valuation'!B16+'DCF Valuation'!C16+'DCF Valuation'!D16+'DCF Valuation'!E16+'DCF Valuation'!F16-'DCF Valuation'!B21 | E6: =('DCF Valuation'!F13*(1+E$5)/($A6-E$5))*'DCF Valuation'!F15+'DCF Valuation'!B16+'DCF Valuation'!C16+'DCF Valuation'!D16+'DCF Valuation'!E16+'DCF Valuation'!F16-'DCF Valuation'!B21 | F6: =('DCF Valuation'!F13*(1+F$5)/($A6-F$5))*'DCF Valuation'!F15+'DCF Valuation'!B16+'DCF Valuation'!C16+'DCF Valuation'!D16+'DCF Valuation'!E16+'DCF Valuation'!F16-'DCF Valuation'!B21
A7: 0.09 | B7: =('DCF Valuation'!F13*(1+B$5)/($A7-B$5))*'DCF Valuation'!F15+'DCF Valuation'!B16+'DCF Valuation'!C16+'DCF Valuation'!D16+'DCF Valuation'!E16+'DCF Valuation'!F16-'DCF Valuation'!B21 | C7: =('DCF Valuation'!F13*(1+C$5)/($A7-C$5))*'DCF Valuation'!F15+'DCF Valuation'!B16+'DCF Valuation'!C16+'DCF Valuation'!D16+'DCF Valuation'!E16+'DCF Valuation'!F16-'DCF Valuation'!B21 | D7: =('DCF Valuation'!F13*(1+D$5)/($A7-D$5))*'DCF Valuation'!F15+'DCF Valuation'!B16+'DCF Valuation'!C16+'DCF Valuation'!D16+'DCF Valuation'!E16+'DCF Valuation'!F16-'DCF Valuation'!B21 | E7: =('DCF Valuation'!F13*(1+E$5)/($A7-E$5))*'DCF Valuation'!F15+'DCF Valuation'!B16+'DCF Valuation'!C16+'DCF Valuation'!D16+'DCF Valuation'!E16+'DCF Valuation'!F16-'DCF Valuation'!B21 | F7: =('DCF Valuation'!F13*(1+F$5)/($A7-F$5))*'DCF Valuation'!F15+'DCF Valuation'!B16+'DCF Valuation'!C16+'DCF Valuation'!D16+'DCF Valuation'!E16+'DCF Valuation'!F16-'DCF Valuation'!B21
A8: 0.095 | B8: =('DCF Valuation'!F13*(1+B$5)/($A8-B$5))*'DCF Valuation'!F15+'DCF Valuation'!B16+'DCF Valuation'!C16+'DCF Valuation'!D16+'DCF Valuation'!E16+'DCF Valuation'!F16-'DCF Valuation'!B21 | C8: =('DCF Valuation'!F13*(1+C$5)/($A8-C$5))*'DCF Valuation'!F15+'DCF Valuation'!B16+'DCF Valuation'!C16+'DCF Valuation'!D16+'DCF Valuation'!E16+'DCF Valuation'!F16-'DCF Valuation'!B21 | D8: =('DCF Valuation'!F13*(1+D$5)/($A8-D$5))*'DCF Valuation'!F15+'DCF Valuation'!B16+'DCF Valuation'!C16+'DCF Valuation'!D16+'DCF Valuation'!E16+'DCF Valuation'!F16-'DCF Valuation'!B21 | E8: =('DCF Valuation'!F13*(1+E$5)/($A8-E$5))*'DCF Valuation'!F15+'DCF Valuation'!B16+'DCF Valuation'!C16+'DCF Valuation'!D16+'DCF Valuation'!E16+'DCF Valuation'!F16-'DCF Valuation'!B21 | F8: =('DCF Valuation'!F13*(1+F$5)/($A8-F$5))*'DCF Valuation'!F15+'DCF Valuation'!B16+'DCF Valuation'!C16+'DCF Valuation'!D16+'DCF Valuation'!E16+'DCF Valuation'!F16-'DCF Valuation'!B21
A9: 0.1 | B9: =('DCF Valuation'!F13*(1+B$5)/($A9-B$5))*'DCF Valuation'!F15+'DCF Valuation'!B16+'DCF Valuation'!C16+'DCF Valuation'!D16+'DCF Valuation'!E16+'DCF Valuation'!F16-'DCF Valuation'!B21 | C9: =('DCF Valuation'!F13*(1+C$5)/($A9-C$5))*'DCF Valuation'!F15+'DCF Valuation'!B16+'DCF Valuation'!C16+'DCF Valuation'!D16+'DCF Valuation'!E16+'DCF Valuation'!F16-'DCF Valuation'!B21 | D9: =('DCF Valuation'!F13*(1+D$5)/($A9-D$5))*'DCF Valuation'!F15+'DCF Valuation'!B16+'DCF Valuation'!C16+'DCF Valuation'!D16+'DCF Valuation'!E16+'DCF Valuation'!F16-'DCF Valuation'!B21 | E9: =('DCF Valuation'!F13*(1+E$5)/($A9-E$5))*'DCF Valuation'!F15+'DCF Valuation'!B16+'DCF Valuation'!C16+'DCF Valuation'!D16+'DCF Valuation'!E16+'DCF Valuation'!F16-'DCF Valuation'!B21 | F9: =('DCF Valuation'!F13*(1+F$5)/($A9-F$5))*'DCF Valuation'!F15+'DCF Valuation'!B16+'DCF Valuation'!C16+'DCF Valuation'!D16+'DCF Valuation'!E16+'DCF Valuation'!F16-'DCF Valuation'!B21
A10: 0.105 | B10: =('DCF Valuation'!F13*(1+B$5)/($A10-B$5))*'DCF Valuation'!F15+'DCF Valuation'!B16+'DCF Valuation'!C16+'DCF Valuation'!D16+'DCF Valuation'!E16+'DCF Valuation'!F16-'DCF Valuation'!B21 | C10: =('DCF Valuation'!F13*(1+C$5)/($A10-C$5))*'DCF Valuation'!F15+'DCF Valuation'!B16+'DCF Valuation'!C16+'DCF Valuation'!D16+'DCF Valuation'!E16+'DCF Valuation'!F16-'DCF Valuation'!B21 | D10: =('DCF Valuation'!F13*(1+D$5)/($A10-D$5))*'DCF Valuation'!F15+'DCF Valuation'!B16+'DCF Valuation'!C16+'DCF Valuation'!D16+'DCF Valuation'!E16+'DCF Valuation'!F16-'DCF Valuation'!B21 | E10: =('DCF Valuation'!F13*(1+E$5)/($A10-E$5))*'DCF Valuation'!F15+'DCF Valuation'!B16+'DCF Valuation'!C16+'DCF Valuation'!D16+'DCF Valuation'!E16+'DCF Valuation'!F16-'DCF Valuation'!B21 | F10: =('DCF Valuation'!F13*(1+F$5)/($A10-F$5))*'DCF Valuation'!F15+'DCF Valuation'!B16+'DCF Valuation'!C16+'DCF Valuation'!D16+'DCF Valuation'!E16+'DCF Valuation'!F16-'DCF Valuation'!B21

Sheet Model Checks
A1: Model Integrity Checks
A2: Check | B2: Formula | C2: Status
A3: Balance Sheet Balances | B3: ='Balance Sheet'!B15 | C3: Should be 0
A4: Balance Sheet Balances FY28E | B4: ='Balance Sheet'!Q15 | C4: Should be 0
A5: DCF Uses Positive WACC | B5: ='DCF Valuation'!B14 | C5: Should be > terminal growth
A6: Forecast EBITDA Margin | B6: ='P&L'!J9 | C6: Should align with assumption
A7: Forecast Store Growth | B7: ='Operating Metrics'!J4 | C7: Driver
